[
  {
    "experiment": "adult",
    "dataset": "Adult (real)",
    "command": "python adult.py",
    "status": "EXECUTED",
    "runtime_s": 2864.62,
    "classifier": "tabicl",
    "test_acc": 80.94,
    "test_f1": 70.78,
    "test_auc": 84.94,
    "wsd": "1-way=0.0292; 2-way=0.0527; 3-way=0.0758",
    "epsilon": 1.0,
    "delta": 2.8805876962760987e-06,
    "notes": "",
    "_source_json": "results/summaries/experiment_adult.json"
  },
  {
    "experiment": "artificial_characters",
    "dataset": "Artificial Characters (real)",
    "command": "python artificial_characters.py",
    "status": "EXECUTED",
    "runtime_s": 224.23,
    "classifier": "tabicl",
    "test_acc": 51.6,
    "test_f1": 50.92,
    "test_auc": "",
    "wsd": "5-way=0.1519; 6-way=0.1862; 7-way=0.2175",
    "epsilon": 1.0,
    "delta": 1.575422064457033e-05,
    "notes": "",
    "_source_json": "results/summaries/experiment_artificial_characters.json"
  },
  {
    "experiment": "breast_cancer",
    "dataset": "Breast Cancer (real)",
    "command": "python breast_cancer.py",
    "status": "EXECUTED",
    "runtime_s": 230.53,
    "classifier": "tabicl",
    "test_acc": 91.86,
    "test_f1": 91.44,
    "test_auc": 98.73,
    "wsd": "1-way=0.1644; 2-way=0.2767; 3-way=0.3749",
    "epsilon": 1.0,
    "delta": 0.00041970816968923,
    "notes": "",
    "_source_json": "results/summaries/smoke_breast_cancer.json"
  },
  {
    "experiment": "person_activity",
    "dataset": "Person Activity (real)",
    "command": "python person_activity.py",
    "status": "EXECUTED",
    "runtime_s": 4497.71,
    "classifier": "tabicl",
    "test_acc": 64.04,
    "test_f1": 36.52,
    "test_auc": "",
    "wsd": "5-way=0.1175; 6-way=0.1526; 7-way=0.1868",
    "epsilon": 1.0,
    "delta": 7.434136520415307e-07,
    "notes": "",
    "_source_json": "results/summaries/experiment_person_activity.json"
  },
  {
    "experiment": "scm_nn",
    "dataset": "SCM (simulated)",
    "command": "python scm.py --prior-function nn",
    "status": "EXECUTED",
    "runtime_s": 745.5,
    "classifier": "tabicl",
    "test_acc": 85.48,
    "test_f1": 85.46,
    "test_auc": 93.8,
    "wsd": "5-way=0.1432; 6-way=0.1817; 7-way=0.2174",
    "epsilon": 1.0,
    "delta": 2.730683970301006e-06,
    "notes": "",
    "_source_json": "results/summaries/experiment_scm_nn.json"
  },
  {
    "experiment": "scm_rff",
    "dataset": "SCM (simulated)",
    "command": "python scm.py --prior-function rff",
    "status": "EXECUTED",
    "runtime_s": 739.31,
    "classifier": "tabicl",
    "test_acc": 61.08,
    "test_f1": 61.03,
    "test_auc": 64.14,
    "wsd": "5-way=0.1460; 6-way=0.1860; 7-way=0.2243",
    "epsilon": 1.0,
    "delta": 2.730683970301006e-06,
    "notes": "",
    "_source_json": "results/summaries/experiment_scm_rff.json"
  },
  {
    "experiment": "scm_tree",
    "dataset": "SCM (simulated)",
    "command": "python scm.py --prior-function tree",
    "status": "EXECUTED",
    "runtime_s": 742.1,
    "classifier": "tabicl",
    "test_acc": 66.68,
    "test_f1": 66.66,
    "test_auc": 72.61,
    "wsd": "5-way=0.1424; 6-way=0.1828; 7-way=0.2210",
    "epsilon": 1.0,
    "delta": 2.730683970301006e-06,
    "notes": "",
    "_source_json": "results/summaries/experiment_scm_tree.json"
  },
  {
    "experiment": "xor_stress_test_1_features",
    "dataset": "XOR stress test (1 feature)",
    "command": "python scripts/experiments/xor_no_classifier.py --num-features 1",
    "status": "EXECUTED",
    "runtime_s": 5.41,
    "classifier": "",
    "test_acc": "",
    "test_f1": "",
    "test_auc": "",
    "wsd": "",
    "epsilon": 1.0,
    "delta": "1/n/ln(n)",
    "notes": "classifier: NOT_RUN (tabpfn requires interactive license/TABPFN_TOKEN) | deviation: TabClassifier(model_name='tabpfn') removed; generation/DP unchanged.",
    "_source_json": "results/summaries/xor_xor_stress_test_1_features.json"
  },
  {
    "experiment": "xor_stress_test_1_features_tabicl",
    "dataset": "XOR stress test (1 feature)",
    "command": "python scripts/experiments/xor_with_classifier.py --num-features 1 --classifier tabicl",
    "status": "EXECUTED",
    "runtime_s": 461.6,
    "classifier": "tabicl",
    "test_acc": 99.8,
    "test_f1": 99.8,
    "test_auc": 100.0,
    "wsd": "",
    "epsilon": 1.0,
    "delta": 2.730683970301006e-06,
    "notes": "deviation: classifier tabpfn -> tabicl (tabpfn is license-gated); generation/DP unchanged.",
    "_source_json": "results/summaries/xor_clf_1f_tabicl.json"
  },
  {
    "experiment": "xor_stress_test_2_features",
    "dataset": "XOR stress test (2 feature)",
    "command": "python scripts/experiments/xor_no_classifier.py --num-features 2",
    "status": "EXECUTED",
    "runtime_s": 5.67,
    "classifier": "",
    "test_acc": "",
    "test_f1": "",
    "test_auc": "",
    "wsd": "",
    "epsilon": 1.0,
    "delta": "1/n/ln(n)",
    "notes": "classifier: NOT_RUN (tabpfn requires interactive license/TABPFN_TOKEN) | deviation: TabClassifier(model_name='tabpfn') removed; generation/DP unchanged.",
    "_source_json": "results/summaries/xor_xor_stress_test_2_features.json"
  },
  {
    "experiment": "xor_stress_test_2_features_tabicl",
    "dataset": "XOR stress test (2 feature)",
    "command": "python scripts/experiments/xor_with_classifier.py --num-features 2 --classifier tabicl",
    "status": "EXECUTED",
    "runtime_s": 963.38,
    "classifier": "tabicl",
    "test_acc": 99.01,
    "test_f1": 99.01,
    "test_auc": 99.96,
    "wsd": "",
    "epsilon": 1.0,
    "delta": 2.730683970301006e-06,
    "notes": "deviation: classifier tabpfn -> tabicl (tabpfn is license-gated); generation/DP unchanged.",
    "_source_json": "results/summaries/xor_clf_2f_tabicl.json"
  },
  {
    "experiment": "xor_stress_test_3_features_tabicl",
    "dataset": "XOR stress test (3 feature)",
    "command": "python scripts/experiments/xor_with_classifier.py --num-features 3 --classifier tabicl",
    "status": "EXECUTED",
    "runtime_s": 1001.12,
    "classifier": "tabicl",
    "test_acc": 96.85,
    "test_f1": 96.85,
    "test_auc": 99.67,
    "wsd": "",
    "epsilon": 1.0,
    "delta": 2.730683970301006e-06,
    "notes": "deviation: classifier tabpfn -> tabicl (tabpfn is license-gated); generation/DP unchanged.",
    "_source_json": "results/summaries/xor_clf_3f_tabicl.json"
  },
  {
    "experiment": "xor_stress_test",
    "dataset": "XOR stress test (simulated)",
    "command": "python xor_stress_test.py --num-features 1",
    "status": "FAILED",
    "runtime_s": 7.82,
    "classifier": "tabpfn",
    "test_acc": "",
    "test_f1": "",
    "test_auc": "",
    "wsd": "",
    "epsilon": 1.0,
    "delta": "1/n/ln(n)",
    "notes": "tabpfn.errors.TabPFNLicenseError: TabPFN requires a one-time license acceptance to download",
    "_source_json": "results/summaries/smoke_xor_stress_test.json"
  }
]